{
  "name": "Orcish Galleon east",
  "bounds": {
    "x1": -9,
    "y1": -4,
    "x2": 14,
    "y2": 3
  },
  "statics": [
    {
      "tile_id": 34468,
      "x": 0,
      "y": 0,
      "z": 0,
      "flags": 0
    },
    {
      "tile_id": 5370,
      "x": 1,
      "y": 2,
      "z": 16,
      "flags": 0
    },
    {
      "tile_id": 5370,
      "x": 1,
      "y": -2,
      "z": 16,
      "flags": 0
    },
    {
      "tile_id": 5370,
      "x": -3,
      "y": -2,
      "z": 16,
      "flags": 0
    },
    {
      "tile_id": 5370,
      "x": -3,
      "y": 2,
      "z": 16,
      "flags": 0
    },
    {
      "tile_id": 5370,
      "x": 6,
      "y": 2,
      "z": 16,
      "flags": 0
    },
    {
      "tile_id": 5370,
      "x": 6,
      "y": -2,
      "z": 16,
      "flags": 0
    },
    {
      "tile_id": 34510,
      "x": -2,
      "y": 0,
      "z": 0,
      "flags": 0
    },
    {
      "tile_id": 34297,
      "x": -5,
      "y": 0,
      "z": 0,
      "flags": 0
    },
    {
      "tile_id": 34298,
      "x": -5,
      "y": -1,
      "z": 0,
      "flags": 0
    },
    {
      "tile_id": 34303,
      "x": -5,
      "y": 1,
      "z": 0,
      "flags": 0
    },
    {
      "tile_id": 34299,
      "x": -5,
      "y": -2,
      "z": 0,
      "flags": 0
    },
    {
      "tile_id": 34301,
      "x": -5,
      "y": 2,
      "z": 0,
      "flags": 0
    },
    {
      "tile_id": 34304,
      "x": -6,
      "y": 0,
      "z": 0,
      "flags": 0
    },
    {
      "tile_id": 34305,
      "x": -6,
      "y": -1,
      "z": 0,
      "flags": 0
    },
    {
      "tile_id": 34310,
      "x": -6,
      "y": 1,
      "z": 0,
      "flags": 0
    },
    {
      "tile_id": 34306,
      "x": -6,
      "y": -2,
      "z": 0,
      "flags": 0
    },
    {
      "tile_id": 34308,
      "x": -6,
      "y": 2,
      "z": 0,
      "flags": 0
    },
    {
      "tile_id": 34311,
      "x": -7,
      "y": 0,
      "z": 0,
      "flags": 0
    },
    {
      "tile_id": 34312,
      "x": -7,
      "y": -1,
      "z": 0,
      "flags": 0
    },
    {
      "tile_id": 34317,
      "x": -7,
      "y": 1,
      "z": 0,
      "flags": 0
    },
    {
      "tile_id": 34313,
      "x": -7,
      "y": -2,
      "z": 0,
      "flags": 0
    },
    {
      "tile_id": 34315,
      "x": -7,
      "y": 2,
      "z": 0,
      "flags": 0
    },
    {
      "tile_id": 34318,
      "x": -8,
      "y": 0,
      "z": 0,
      "flags": 0
    },
    {
      "tile_id": 34319,
      "x": -8,
      "y": -1,
      "z": 0,
      "flags": 0
    },
    {
      "tile_id": 34324,
      "x": -8,
      "y": 1,
      "z": 0,
      "flags": 0
    },
    {
      "tile_id": 34320,
      "x": -8,
      "y": -2,
      "z": 0,
      "flags": 0
    },
    {
      "tile_id": 34322,
      "x": -8,
      "y": 2,
      "z": 0,
      "flags": 0
    },
    {
      "tile_id": 34265,
      "x": -1,
      "y": -2,
      "z": 0,
      "flags": 0
    },
    {
      "tile_id": 34267,
      "x": -1,
      "y": 2,
      "z": 0,
      "flags": 0
    },
    {
      "tile_id": 34373,
      "x": 8,
      "y": 0,
      "z": 0,
      "flags": 0
    },
    {
      "tile_id": 34348,
      "x": 5,
      "y": -2,
      "z": 0,
      "flags": 0
    },
    {
      "tile_id": 34350,
      "x": 5,
      "y": 2,
      "z": 0,
      "flags": 0
    },
    {
      "tile_id": 34232,
      "x": 2,
      "y": -2,
      "z": 0,
      "flags": 0
    },
    {
      "tile_id": 34237,
      "x": 2,
      "y": 2,
      "z": 0,
      "flags": 0
    },
    {
      "tile_id": 34250,
      "x": 0,
      "y": 0,
      "z": 0,
      "flags": 1
    },
    {
      "tile_id": 34243,
      "x": 1,
      "y": 0,
      "z": 0,
      "flags": 1
    },
    {
      "tile_id": 34251,
      "x": 0,
      "y": -1,
      "z": 0,
      "flags": 1
    },
    {
      "tile_id": 34261,
      "x": 0,
      "y": 1,
      "z": 0,
      "flags": 1
    },
    {
      "tile_id": 34263,
      "x": -1,
      "y": 0,
      "z": 0,
      "flags": 1
    },
    {
      "tile_id": 34465,
      "x": -1,
      "y": 0,
      "z": 0,
      "flags": 1
    },
    {
      "tile_id": 34467,
      "x": 0,
      "y": -1,
      "z": 0,
      "flags": 1
    },
    {
      "tile_id": 34470,
      "x": 1,
      "y": 0,
      "z": 0,
      "flags": 1
    },
    {
      "tile_id": 34244,
      "x": 1,
      "y": -1,
      "z": 0,
      "flags": 1
    },
    {
      "tile_id": 34249,
      "x": 1,
      "y": 1,
      "z": 0,
      "flags": 1
    },
    {
      "tile_id": 34264,
      "x": -1,
      "y": -1,
      "z": 0,
      "flags": 1
    },
    {
      "tile_id": 34269,
      "x": -1,
      "y": 1,
      "z": 0,
      "flags": 1
    },
    {
      "tile_id": 34464,
      "x": -1,
      "y": -1,
      "z": 0,
      "flags": 1
    },
    {
      "tile_id": 34469,
      "x": 1,
      "y": -1,
      "z": 0,
      "flags": 1
    },
    {
      "tile_id": 34230,
      "x": 2,
      "y": 0,
      "z": 0,
      "flags": 1
    },
    {
      "tile_id": 34252,
      "x": 0,
      "y": -2,
      "z": 0,
      "flags": 1
    },
    {
      "tile_id": 34257,
      "x": 0,
      "y": 2,
      "z": 0,
      "flags": 1
    },
    {
      "tile_id": 34270,
      "x": -2,
      "y": 0,
      "z": 0,
      "flags": 1
    },
    {
      "tile_id": 34461,
      "x": -2,
      "y": 0,
      "z": 0,
      "flags": 1
    },
    {
      "tile_id": 34474,
      "x": 2,
      "y": 0,
      "z": 0,
      "flags": 1
    },
    {
      "tile_id": 34231,
      "x": 2,
      "y": -1,
      "z": 0,
      "flags": 1
    },
    {
      "tile_id": 34241,
      "x": 2,
      "y": 1,
      "z": 0,
      "flags": 1
    },
    {
      "tile_id": 34245,
      "x": 1,
      "y": -2,
      "z": 0,
      "flags": 1
    },
    {
      "tile_id": 34247,
      "x": 1,
      "y": 2,
      "z": 0,
      "flags": 1
    },
    {
      "tile_id": 34271,
      "x": -2,
      "y": -1,
      "z": 0,
      "flags": 1
    },
    {
      "tile_id": 34281,
      "x": -2,
      "y": 1,
      "z": 0,
      "flags": 1
    },
    {
      "tile_id": 34460,
      "x": -2,
      "y": -1,
      "z": 0,
      "flags": 1
    },
    {
      "tile_id": 34463,
      "x": -1,
      "y": -2,
      "z": 0,
      "flags": 1
    },
    {
      "tile_id": 34473,
      "x": 2,
      "y": -1,
      "z": 0,
      "flags": 1
    },
    {
      "tile_id": 34483,
      "x": 1,
      "y": -2,
      "z": 0,
      "flags": 1
    },
    {
      "tile_id": 34272,
      "x": -2,
      "y": -2,
      "z": 0,
      "flags": 1
    },
    {
      "tile_id": 34277,
      "x": -2,
      "y": 2,
      "z": 0,
      "flags": 1
    },
    {
      "tile_id": 34459,
      "x": -2,
      "y": -2,
      "z": 0,
      "flags": 1
    },
    {
      "tile_id": 34472,
      "x": 2,
      "y": -2,
      "z": 0,
      "flags": 1
    },
    {
      "tile_id": 34223,
      "x": 3,
      "y": 0,
      "z": 0,
      "flags": 1
    },
    {
      "tile_id": 34253,
      "x": 0,
      "y": -3,
      "z": 0,
      "flags": 1
    },
    {
      "tile_id": 34260,
      "x": 0,
      "y": 3,
      "z": 0,
      "flags": 1
    },
    {
      "tile_id": 34283,
      "x": -3,
      "y": 0,
      "z": 0,
      "flags": 1
    },
    {
      "tile_id": 34456,
      "x": -3,
      "y": 0,
      "z": 0,
      "flags": 1
    },
    {
      "tile_id": 34478,
      "x": 3,
      "y": 0,
      "z": 0,
      "flags": 1
    },
    {
      "tile_id": 34224,
      "x": 3,
      "y": -1,
      "z": 0,
      "flags": 1
    },
    {
      "tile_id": 34229,
      "x": 3,
      "y": 1,
      "z": 0,
      "flags": 1
    },
    {
      "tile_id": 34246,
      "x": 1,
      "y": -3,
      "z": 0,
      "flags": 1
    },
    {
      "tile_id": 34248,
      "x": 1,
      "y": 3,
      "z": 0,
      "flags": 1
    },
    {
      "tile_id": 34266,
      "x": -1,
      "y": -3,
      "z": 0,
      "flags": 1
    },
    {
      "tile_id": 34268,
      "x": -1,
      "y": 3,
      "z": 0,
      "flags": 1
    },
    {
      "tile_id": 34284,
      "x": -3,
      "y": -1,
      "z": 0,
      "flags": 1
    },
    {
      "tile_id": 34289,
      "x": -3,
      "y": 1,
      "z": 0,
      "flags": 1
    },
    {
      "tile_id": 34455,
      "x": -3,
      "y": -1,
      "z": 0,
      "flags": 1
    },
    {
      "tile_id": 34477,
      "x": 3,
      "y": -1,
      "z": 0,
      "flags": 1
    },
    {
      "tile_id": 34487,
      "x": 1,
      "y": -3,
      "z": 0,
      "flags": 1
    },
    {
      "tile_id": 34225,
      "x": 3,
      "y": -2,
      "z": 0,
      "flags": 1
    },
    {
      "tile_id": 34227,
      "x": 3,
      "y": 2,
      "z": 0,
      "flags": 1
    },
    {
      "tile_id": 34233,
      "x": 2,
      "y": -3,
      "z": 0,
      "flags": 1
    },
    {
      "tile_id": 34240,
      "x": 2,
      "y": 3,
      "z": 0,
      "flags": 1
    },
    {
      "tile_id": 34273,
      "x": -2,
      "y": -3,
      "z": 0,
      "flags": 1
    },
    {
      "tile_id": 34280,
      "x": -2,
      "y": 3,
      "z": 0,
      "flags": 1
    },
    {
      "tile_id": 34285,
      "x": -3,
      "y": -2,
      "z": 0,
      "flags": 1
    },
    {
      "tile_id": 34287,
      "x": -3,
      "y": 2,
      "z": 0,
      "flags": 1
    },
    {
      "tile_id": 34454,
      "x": -3,
      "y": -2,
      "z": 0,
      "flags": 1
    },
    {
      "tile_id": 34458,
      "x": -2,
      "y": -3,
      "z": 0,
      "flags": 1
    },
    {
      "tile_id": 34471,
      "x": 2,
      "y": -3,
      "z": 0,
      "flags": 1
    },
    {
      "tile_id": 34476,
      "x": 3,
      "y": -2,
      "z": 0,
      "flags": 1
    },
    {
      "tile_id": 34210,
      "x": 4,
      "y": 0,
      "z": 0,
      "flags": 1
    },
    {
      "tile_id": 34290,
      "x": -4,
      "y": 0,
      "z": 0,
      "flags": 1
    },
    {
      "tile_id": 34451,
      "x": -4,
      "y": 0,
      "z": 0,
      "flags": 1
    },
    {
      "tile_id": 34482,
      "x": 4,
      "y": 0,
      "z": 0,
      "flags": 1
    },
    {
      "tile_id": 34211,
      "x": 4,
      "y": -1,
      "z": 0,
      "flags": 1
    },
    {
      "tile_id": 34221,
      "x": 4,
      "y": 1,
      "z": 0,
      "flags": 1
    },
    {
      "tile_id": 34291,
      "x": -4,
      "y": -1,
      "z": 0,
      "flags": 1
    },
    {
      "tile_id": 34296,
      "x": -4,
      "y": 1,
      "z": 0,
      "flags": 1
    },
    {
      "tile_id": 34450,
      "x": -4,
      "y": -1,
      "z": 0,
      "flags": 1
    },
    {
      "tile_id": 34481,
      "x": 4,
      "y": -1,
      "z": 0,
      "flags": 1
    },
    {
      "tile_id": 34226,
      "x": 3,
      "y": -3,
      "z": 0,
      "flags": 1
    },
    {
      "tile_id": 34228,
      "x": 3,
      "y": 3,
      "z": 0,
      "flags": 1
    },
    {
      "tile_id": 34286,
      "x": -3,
      "y": -3,
      "z": 0,
      "flags": 1
    },
    {
      "tile_id": 34288,
      "x": -3,
      "y": 3,
      "z": 0,
      "flags": 1
    },
    {
      "tile_id": 34453,
      "x": -3,
      "y": -3,
      "z": 0,
      "flags": 1
    },
    {
      "tile_id": 34475,
      "x": 3,
      "y": -3,
      "z": 0,
      "flags": 1
    },
    {
      "tile_id": 34212,
      "x": 4,
      "y": -2,
      "z": 0,
      "flags": 1
    },
    {
      "tile_id": 34217,
      "x": 4,
      "y": 2,
      "z": 0,
      "flags": 1
    },
    {
      "tile_id": 34292,
      "x": -4,
      "y": -2,
      "z": 0,
      "flags": 1
    },
    {
      "tile_id": 34294,
      "x": -4,
      "y": 2,
      "z": 0,
      "flags": 1
    },
    {
      "tile_id": 34449,
      "x": -4,
      "y": -2,
      "z": 0,
      "flags": 1
    },
    {
      "tile_id": 34480,
      "x": 4,
      "y": -2,
      "z": 0,
      "flags": 1
    },
    {
      "tile_id": 34213,
      "x": 4,
      "y": -3,
      "z": 0,
      "flags": 1
    },
    {
      "tile_id": 34220,
      "x": 4,
      "y": 3,
      "z": 0,
      "flags": 1
    },
    {
      "tile_id": 34293,
      "x": -4,
      "y": -3,
      "z": 0,
      "flags": 1
    },
    {
      "tile_id": 34295,
      "x": -4,
      "y": 3,
      "z": 0,
      "flags": 1
    },
    {
      "tile_id": 34346,
      "x": 5,
      "y": 0,
      "z": 0,
      "flags": 1
    },
    {
      "tile_id": 34446,
      "x": -5,
      "y": 0,
      "z": 0,
      "flags": 1
    },
    {
      "tile_id": 34448,
      "x": -4,
      "y": -3,
      "z": 0,
      "flags": 1
    },
    {
      "tile_id": 34457,
      "x": -3,
      "y": -4,
      "z": 0,
      "flags": 1
    },
    {
      "tile_id": 34479,
      "x": 4,
      "y": -3,
      "z": 0,
      "flags": 1
    },
    {
      "tile_id": 34486,
      "x": 5,
      "y": 0,
      "z": 0,
      "flags": 1
    },
    {
      "tile_id": 34347,
      "x": 5,
      "y": -1,
      "z": 0,
      "flags": 1
    },
    {
      "tile_id": 34352,
      "x": 5,
      "y": 1,
      "z": 0,
      "flags": 1
    },
    {
      "tile_id": 34445,
      "x": -5,
      "y": -1,
      "z": 0,
      "flags": 1
    },
    {
      "tile_id": 34485,
      "x": 5,
      "y": -1,
      "z": 0,
      "flags": 1
    },
    {
      "tile_id": 34444,
      "x": -5,
      "y": -2,
      "z": 0,
      "flags": 1
    },
    {
      "tile_id": 34484,
      "x": 5,
      "y": -2,
      "z": 0,
      "flags": 1
    },
    {
      "tile_id": 34452,
      "x": -4,
      "y": -4,
      "z": 0,
      "flags": 1
    },
    {
      "tile_id": 34300,
      "x": -5,
      "y": -3,
      "z": 0,
      "flags": 1
    },
    {
      "tile_id": 34302,
      "x": -5,
      "y": 3,
      "z": 0,
      "flags": 1
    },
    {
      "tile_id": 34349,
      "x": 5,
      "y": -3,
      "z": 0,
      "flags": 1
    },
    {
      "tile_id": 34351,
      "x": 5,
      "y": 3,
      "z": 0,
      "flags": 1
    },
    {
      "tile_id": 34443,
      "x": -5,
      "y": -3,
      "z": 0,
      "flags": 1
    },
    {
      "tile_id": 34353,
      "x": 6,
      "y": 0,
      "z": 0,
      "flags": 1
    },
    {
      "tile_id": 34489,
      "x": 6,
      "y": 0,
      "z": 0,
      "flags": 1
    },
    {
      "tile_id": 34354,
      "x": 6,
      "y": -1,
      "z": 0,
      "flags": 1
    },
    {
      "tile_id": 34364,
      "x": 6,
      "y": 1,
      "z": 0,
      "flags": 1
    },
    {
      "tile_id": 34488,
      "x": 6,
      "y": -1,
      "z": 0,
      "flags": 1
    },
    {
      "tile_id": 34355,
      "x": 6,
      "y": -2,
      "z": 0,
      "flags": 1
    },
    {
      "tile_id": 34360,
      "x": 6,
      "y": 2,
      "z": 0,
      "flags": 1
    },
    {
      "tile_id": 34447,
      "x": -5,
      "y": -4,
      "z": 0,
      "flags": 1
    },
    {
      "tile_id": 34307,
      "x": -6,
      "y": -3,
      "z": 0,
      "flags": 1
    },
    {
      "tile_id": 34309,
      "x": -6,
      "y": 3,
      "z": 0,
      "flags": 1
    },
    {
      "tile_id": 34356,
      "x": 6,
      "y": -3,
      "z": 0,
      "flags": 1
    },
    {
      "tile_id": 34363,
      "x": 6,
      "y": 3,
      "z": 0,
      "flags": 1
    },
    {
      "tile_id": 34438,
      "x": -6,
      "y": -3,
      "z": 0,
      "flags": 1
    },
    {
      "tile_id": 34366,
      "x": 7,
      "y": 0,
      "z": 0,
      "flags": 1
    },
    {
      "tile_id": 34491,
      "x": 7,
      "y": 0,
      "z": 0,
      "flags": 1
    },
    {
      "tile_id": 34367,
      "x": 7,
      "y": -1,
      "z": 0,
      "flags": 1
    },
    {
      "tile_id": 34372,
      "x": 7,
      "y": 1,
      "z": 0,
      "flags": 1
    },
    {
      "tile_id": 34490,
      "x": 7,
      "y": -1,
      "z": 0,
      "flags": 1
    },
    {
      "tile_id": 34442,
      "x": -6,
      "y": -4,
      "z": 0,
      "flags": 1
    },
    {
      "tile_id": 34368,
      "x": 7,
      "y": -2,
      "z": 0,
      "flags": 1
    },
    {
      "tile_id": 34370,
      "x": 7,
      "y": 2,
      "z": 0,
      "flags": 1
    },
    {
      "tile_id": 34497,
      "x": 7,
      "y": -2,
      "z": 0,
      "flags": 1
    },
    {
      "tile_id": 34314,
      "x": -7,
      "y": -3,
      "z": 0,
      "flags": 1
    },
    {
      "tile_id": 34316,
      "x": -7,
      "y": 3,
      "z": 0,
      "flags": 1
    },
    {
      "tile_id": 34369,
      "x": 7,
      "y": -3,
      "z": 0,
      "flags": 1
    },
    {
      "tile_id": 34371,
      "x": 7,
      "y": 3,
      "z": 0,
      "flags": 1
    },
    {
      "tile_id": 34436,
      "x": -7,
      "y": -3,
      "z": 0,
      "flags": 1
    },
    {
      "tile_id": 34374,
      "x": 8,
      "y": -1,
      "z": 0,
      "flags": 1
    },
    {
      "tile_id": 34384,
      "x": 8,
      "y": 1,
      "z": 0,
      "flags": 1
    },
    {
      "tile_id": 34492,
      "x": 8,
      "y": -1,
      "z": 0,
      "flags": 1
    },
    {
      "tile_id": 34375,
      "x": 8,
      "y": -2,
      "z": 0,
      "flags": 1
    },
    {
      "tile_id": 34380,
      "x": 8,
      "y": 2,
      "z": 0,
      "flags": 1
    },
    {
      "tile_id": 34432,
      "x": -8,
      "y": -2,
      "z": 0,
      "flags": 1
    },
    {
      "tile_id": 34499,
      "x": 8,
      "y": -2,
      "z": 0,
      "flags": 1
    },
    {
      "tile_id": 34321,
      "x": -8,
      "y": -3,
      "z": 0,
      "flags": 1
    },
    {
      "tile_id": 34323,
      "x": -8,
      "y": 3,
      "z": 0,
      "flags": 1
    },
    {
      "tile_id": 34376,
      "x": 8,
      "y": -3,
      "z": 0,
      "flags": 1
    },
    {
      "tile_id": 34383,
      "x": 8,
      "y": 3,
      "z": 0,
      "flags": 1
    },
    {
      "tile_id": 34435,
      "x": -8,
      "y": -3,
      "z": 0,
      "flags": 1
    },
    {
      "tile_id": 34325,
      "x": -9,
      "y": 0,
      "z": 0,
      "flags": 1
    },
    {
      "tile_id": 34386,
      "x": 9,
      "y": 0,
      "z": 0,
      "flags": 1
    },
    {
      "tile_id": 34326,
      "x": -9,
      "y": -1,
      "z": 0,
      "flags": 1
    },
    {
      "tile_id": 34331,
      "x": -9,
      "y": 1,
      "z": 0,
      "flags": 1
    },
    {
      "tile_id": 34387,
      "x": 9,
      "y": -1,
      "z": 0,
      "flags": 1
    },
    {
      "tile_id": 34392,
      "x": 9,
      "y": 1,
      "z": 0,
      "flags": 1
    },
    {
      "tile_id": 34495,
      "x": 9,
      "y": -1,
      "z": 0,
      "flags": 1
    },
    {
      "tile_id": 34327,
      "x": -9,
      "y": -2,
      "z": 0,
      "flags": 1
    },
    {
      "tile_id": 34329,
      "x": -9,
      "y": 2,
      "z": 0,
      "flags": 1
    },
    {
      "tile_id": 34388,
      "x": 9,
      "y": -2,
      "z": 0,
      "flags": 1
    },
    {
      "tile_id": 34390,
      "x": 9,
      "y": 2,
      "z": 0,
      "flags": 1
    },
    {
      "tile_id": 34434,
      "x": -9,
      "y": -2,
      "z": 0,
      "flags": 1
    },
    {
      "tile_id": 34494,
      "x": 9,
      "y": -2,
      "z": 0,
      "flags": 1
    },
    {
      "tile_id": 34328,
      "x": -9,
      "y": -3,
      "z": 0,
      "flags": 1
    },
    {
      "tile_id": 34330,
      "x": -9,
      "y": 3,
      "z": 0,
      "flags": 1
    },
    {
      "tile_id": 34393,
      "x": 10,
      "y": 0,
      "z": 0,
      "flags": 1
    },
    {
      "tile_id": 34394,
      "x": 10,
      "y": -1,
      "z": 0,
      "flags": 1
    },
    {
      "tile_id": 34399,
      "x": 10,
      "y": 1,
      "z": 0,
      "flags": 1
    },
    {
      "tile_id": 34498,
      "x": 10,
      "y": -1,
      "z": 0,
      "flags": 1
    },
    {
      "tile_id": 34395,
      "x": 10,
      "y": -2,
      "z": 0,
      "flags": 1
    },
    {
      "tile_id": 34397,
      "x": 10,
      "y": 2,
      "z": 0,
      "flags": 1
    },
    {
      "tile_id": 34400,
      "x": 11,
      "y": 0,
      "z": 0,
      "flags": 1
    },
    {
      "tile_id": 34401,
      "x": 11,
      "y": -1,
      "z": 0,
      "flags": 1
    },
    {
      "tile_id": 34406,
      "x": 11,
      "y": 1,
      "z": 0,
      "flags": 1
    },
    {
      "tile_id": 34500,
      "x": 11,
      "y": -1,
      "z": 0,
      "flags": 1
    },
    {
      "tile_id": 34404,
      "x": 11,
      "y": 2,
      "z": 0,
      "flags": 1
    },
    {
      "tile_id": 34407,
      "x": 12,
      "y": 0,
      "z": 0,
      "flags": 1
    },
    {
      "tile_id": 34501,
      "x": 12,
      "y": 0,
      "z": 0,
      "flags": 1
    },
    {
      "tile_id": 34408,
      "x": 12,
      "y": -1,
      "z": 0,
      "flags": 1
    },
    {
      "tile_id": 34411,
      "x": 12,
      "y": 1,
      "z": 0,
      "flags": 1
    },
    {
      "tile_id": 34502,
      "x": 12,
      "y": -1,
      "z": 0,
      "flags": 1
    },
    {
      "tile_id": 34412,
      "x": 13,
      "y": 0,
      "z": 0,
      "flags": 1
    },
    {
      "tile_id": 34504,
      "x": 13,
      "y": 0,
      "z": 0,
      "flags": 1
    },
    {
      "tile_id": 34413,
      "x": 13,
      "y": -1,
      "z": 0,
      "flags": 1
    },
    {
      "tile_id": 34416,
      "x": 13,
      "y": 1,
      "z": 0,
      "flags": 1
    },
    {
      "tile_id": 34417,
      "x": 14,
      "y": 0,
      "z": 0,
      "flags": 1
    }
  ],
  "doors": []
}
