{
  "name": "Gargish Galleon destroyed north",
  "bounds": {
    "x1": -3,
    "y1": -14,
    "x2": 3,
    "y2": 9
  },
  "statics": [
    {
      "tile_id": 36274,
      "x": 0,
      "y": 0,
      "z": 0,
      "flags": 0
    },
    {
      "tile_id": 5370,
      "x": 2,
      "y": -1,
      "z": 16,
      "flags": 0
    },
    {
      "tile_id": 5370,
      "x": -2,
      "y": -1,
      "z": 16,
      "flags": 0
    },
    {
      "tile_id": 5370,
      "x": -2,
      "y": 3,
      "z": 16,
      "flags": 0
    },
    {
      "tile_id": 5370,
      "x": 2,
      "y": 3,
      "z": 16,
      "flags": 0
    },
    {
      "tile_id": 5370,
      "x": 2,
      "y": -6,
      "z": 16,
      "flags": 0
    },
    {
      "tile_id": 5370,
      "x": -2,
      "y": -6,
      "z": 16,
      "flags": 0
    },
    {
      "tile_id": 36322,
      "x": 0,
      "y": 2,
      "z": 0,
      "flags": 0
    },
    {
      "tile_id": 36084,
      "x": 0,
      "y": 5,
      "z": 0,
      "flags": 0
    },
    {
      "tile_id": 36085,
      "x": -1,
      "y": 5,
      "z": 0,
      "flags": 0
    },
    {
      "tile_id": 36090,
      "x": 1,
      "y": 5,
      "z": 0,
      "flags": 0
    },
    {
      "tile_id": 36086,
      "x": -2,
      "y": 5,
      "z": 0,
      "flags": 0
    },
    {
      "tile_id": 36088,
      "x": 2,
      "y": 5,
      "z": 0,
      "flags": 0
    },
    {
      "tile_id": 36091,
      "x": 0,
      "y": 6,
      "z": 0,
      "flags": 0
    },
    {
      "tile_id": 36092,
      "x": -1,
      "y": 6,
      "z": 0,
      "flags": 0
    },
    {
      "tile_id": 36097,
      "x": 1,
      "y": 6,
      "z": 0,
      "flags": 0
    },
    {
      "tile_id": 36093,
      "x": -2,
      "y": 6,
      "z": 0,
      "flags": 0
    },
    {
      "tile_id": 36095,
      "x": 2,
      "y": 6,
      "z": 0,
      "flags": 0
    },
    {
      "tile_id": 36098,
      "x": 0,
      "y": 7,
      "z": 0,
      "flags": 0
    },
    {
      "tile_id": 36099,
      "x": -1,
      "y": 7,
      "z": 0,
      "flags": 0
    },
    {
      "tile_id": 36104,
      "x": 1,
      "y": 7,
      "z": 0,
      "flags": 0
    },
    {
      "tile_id": 36100,
      "x": -2,
      "y": 7,
      "z": 0,
      "flags": 0
    },
    {
      "tile_id": 36102,
      "x": 2,
      "y": 7,
      "z": 0,
      "flags": 0
    },
    {
      "tile_id": 36105,
      "x": 0,
      "y": 8,
      "z": 0,
      "flags": 0
    },
    {
      "tile_id": 36106,
      "x": -1,
      "y": 8,
      "z": 0,
      "flags": 0
    },
    {
      "tile_id": 36111,
      "x": 1,
      "y": 8,
      "z": 0,
      "flags": 0
    },
    {
      "tile_id": 36107,
      "x": -2,
      "y": 8,
      "z": 0,
      "flags": 0
    },
    {
      "tile_id": 36109,
      "x": 2,
      "y": 8,
      "z": 0,
      "flags": 0
    },
    {
      "tile_id": 36058,
      "x": -2,
      "y": 1,
      "z": 0,
      "flags": 0
    },
    {
      "tile_id": 36060,
      "x": 2,
      "y": 1,
      "z": 0,
      "flags": 0
    },
    {
      "tile_id": 36140,
      "x": 0,
      "y": -8,
      "z": 0,
      "flags": 0
    },
    {
      "tile_id": 36121,
      "x": -2,
      "y": -5,
      "z": 0,
      "flags": 0
    },
    {
      "tile_id": 36123,
      "x": 2,
      "y": -5,
      "z": 0,
      "flags": 0
    },
    {
      "tile_id": 36037,
      "x": -2,
      "y": -2,
      "z": 0,
      "flags": 0
    },
    {
      "tile_id": 36039,
      "x": 2,
      "y": -2,
      "z": 0,
      "flags": 0
    },
    {
      "tile_id": 36049,
      "x": 0,
      "y": 0,
      "z": 0,
      "flags": 1
    },
    {
      "tile_id": 36042,
      "x": 0,
      "y": -1,
      "z": 0,
      "flags": 1
    },
    {
      "tile_id": 36050,
      "x": -1,
      "y": 0,
      "z": 0,
      "flags": 1
    },
    {
      "tile_id": 36055,
      "x": 1,
      "y": 0,
      "z": 0,
      "flags": 1
    },
    {
      "tile_id": 36056,
      "x": 0,
      "y": 1,
      "z": 0,
      "flags": 1
    },
    {
      "tile_id": 36273,
      "x": 0,
      "y": -1,
      "z": 0,
      "flags": 1
    },
    {
      "tile_id": 36279,
      "x": 0,
      "y": 1,
      "z": 0,
      "flags": 1
    },
    {
      "tile_id": 36284,
      "x": -1,
      "y": 0,
      "z": 0,
      "flags": 1
    },
    {
      "tile_id": 36043,
      "x": -1,
      "y": -1,
      "z": 0,
      "flags": 1
    },
    {
      "tile_id": 36048,
      "x": 1,
      "y": -1,
      "z": 0,
      "flags": 1
    },
    {
      "tile_id": 36057,
      "x": -1,
      "y": 1,
      "z": 0,
      "flags": 1
    },
    {
      "tile_id": 36062,
      "x": 1,
      "y": 1,
      "z": 0,
      "flags": 1
    },
    {
      "tile_id": 36272,
      "x": -1,
      "y": -1,
      "z": 0,
      "flags": 1
    },
    {
      "tile_id": 36281,
      "x": -1,
      "y": 1,
      "z": 0,
      "flags": 1
    },
    {
      "tile_id": 36035,
      "x": 0,
      "y": -2,
      "z": 0,
      "flags": 1
    },
    {
      "tile_id": 36051,
      "x": -2,
      "y": 0,
      "z": 0,
      "flags": 1
    },
    {
      "tile_id": 36053,
      "x": 2,
      "y": 0,
      "z": 0,
      "flags": 1
    },
    {
      "tile_id": 36063,
      "x": 0,
      "y": 2,
      "z": 0,
      "flags": 1
    },
    {
      "tile_id": 36276,
      "x": 0,
      "y": 2,
      "z": 0,
      "flags": 1
    },
    {
      "tile_id": 36036,
      "x": -1,
      "y": -2,
      "z": 0,
      "flags": 1
    },
    {
      "tile_id": 36041,
      "x": 1,
      "y": -2,
      "z": 0,
      "flags": 1
    },
    {
      "tile_id": 36044,
      "x": -2,
      "y": -1,
      "z": 0,
      "flags": 1
    },
    {
      "tile_id": 36046,
      "x": 2,
      "y": -1,
      "z": 0,
      "flags": 1
    },
    {
      "tile_id": 36064,
      "x": -1,
      "y": 2,
      "z": 0,
      "flags": 1
    },
    {
      "tile_id": 36069,
      "x": 1,
      "y": 2,
      "z": 0,
      "flags": 1
    },
    {
      "tile_id": 36269,
      "x": -1,
      "y": -2,
      "z": 0,
      "flags": 1
    },
    {
      "tile_id": 36271,
      "x": -2,
      "y": -1,
      "z": 0,
      "flags": 1
    },
    {
      "tile_id": 36282,
      "x": -1,
      "y": 2,
      "z": 0,
      "flags": 1
    },
    {
      "tile_id": 36065,
      "x": -2,
      "y": 2,
      "z": 0,
      "flags": 1
    },
    {
      "tile_id": 36067,
      "x": 2,
      "y": 2,
      "z": 0,
      "flags": 1
    },
    {
      "tile_id": 36270,
      "x": -2,
      "y": -2,
      "z": 0,
      "flags": 1
    },
    {
      "tile_id": 36028,
      "x": 0,
      "y": -3,
      "z": 0,
      "flags": 1
    },
    {
      "tile_id": 36052,
      "x": -3,
      "y": 0,
      "z": 0,
      "flags": 1
    },
    {
      "tile_id": 36054,
      "x": 3,
      "y": 0,
      "z": 0,
      "flags": 1
    },
    {
      "tile_id": 36070,
      "x": 0,
      "y": 3,
      "z": 0,
      "flags": 1
    },
    {
      "tile_id": 36266,
      "x": 0,
      "y": -3,
      "z": 0,
      "flags": 1
    },
    {
      "tile_id": 36278,
      "x": 0,
      "y": 3,
      "z": 0,
      "flags": 1
    },
    {
      "tile_id": 36029,
      "x": -1,
      "y": -3,
      "z": 0,
      "flags": 1
    },
    {
      "tile_id": 36034,
      "x": 1,
      "y": -3,
      "z": 0,
      "flags": 1
    },
    {
      "tile_id": 36045,
      "x": -3,
      "y": -1,
      "z": 0,
      "flags": 1
    },
    {
      "tile_id": 36047,
      "x": 3,
      "y": -1,
      "z": 0,
      "flags": 1
    },
    {
      "tile_id": 36059,
      "x": -3,
      "y": 1,
      "z": 0,
      "flags": 1
    },
    {
      "tile_id": 36061,
      "x": 3,
      "y": 1,
      "z": 0,
      "flags": 1
    },
    {
      "tile_id": 36071,
      "x": -1,
      "y": 3,
      "z": 0,
      "flags": 1
    },
    {
      "tile_id": 36076,
      "x": 1,
      "y": 3,
      "z": 0,
      "flags": 1
    },
    {
      "tile_id": 36265,
      "x": -1,
      "y": -3,
      "z": 0,
      "flags": 1
    },
    {
      "tile_id": 36283,
      "x": -1,
      "y": 3,
      "z": 0,
      "flags": 1
    },
    {
      "tile_id": 36030,
      "x": -2,
      "y": -3,
      "z": 0,
      "flags": 1
    },
    {
      "tile_id": 36032,
      "x": 2,
      "y": -3,
      "z": 0,
      "flags": 1
    },
    {
      "tile_id": 36038,
      "x": -3,
      "y": -2,
      "z": 0,
      "flags": 1
    },
    {
      "tile_id": 36040,
      "x": 3,
      "y": -2,
      "z": 0,
      "flags": 1
    },
    {
      "tile_id": 36066,
      "x": -3,
      "y": 2,
      "z": 0,
      "flags": 1
    },
    {
      "tile_id": 36068,
      "x": 3,
      "y": 2,
      "z": 0,
      "flags": 1
    },
    {
      "tile_id": 36072,
      "x": -2,
      "y": 3,
      "z": 0,
      "flags": 1
    },
    {
      "tile_id": 36074,
      "x": 2,
      "y": 3,
      "z": 0,
      "flags": 1
    },
    {
      "tile_id": 36267,
      "x": -2,
      "y": -3,
      "z": 0,
      "flags": 1
    },
    {
      "tile_id": 36021,
      "x": 0,
      "y": -4,
      "z": 0,
      "flags": 1
    },
    {
      "tile_id": 36077,
      "x": 0,
      "y": 4,
      "z": 0,
      "flags": 1
    },
    {
      "tile_id": 36261,
      "x": 0,
      "y": -4,
      "z": 0,
      "flags": 1
    },
    {
      "tile_id": 36277,
      "x": 0,
      "y": 4,
      "z": 0,
      "flags": 1
    },
    {
      "tile_id": 36022,
      "x": -1,
      "y": -4,
      "z": 0,
      "flags": 1
    },
    {
      "tile_id": 36027,
      "x": 1,
      "y": -4,
      "z": 0,
      "flags": 1
    },
    {
      "tile_id": 36078,
      "x": -1,
      "y": 4,
      "z": 0,
      "flags": 1
    },
    {
      "tile_id": 36083,
      "x": 1,
      "y": 4,
      "z": 0,
      "flags": 1
    },
    {
      "tile_id": 36264,
      "x": -1,
      "y": -4,
      "z": 0,
      "flags": 1
    },
    {
      "tile_id": 36280,
      "x": -1,
      "y": 4,
      "z": 0,
      "flags": 1
    },
    {
      "tile_id": 36031,
      "x": -3,
      "y": -3,
      "z": 0,
      "flags": 1
    },
    {
      "tile_id": 36033,
      "x": 3,
      "y": -3,
      "z": 0,
      "flags": 1
    },
    {
      "tile_id": 36073,
      "x": -3,
      "y": 3,
      "z": 0,
      "flags": 1
    },
    {
      "tile_id": 36075,
      "x": 3,
      "y": 3,
      "z": 0,
      "flags": 1
    },
    {
      "tile_id": 36023,
      "x": -2,
      "y": -4,
      "z": 0,
      "flags": 1
    },
    {
      "tile_id": 36025,
      "x": 2,
      "y": -4,
      "z": 0,
      "flags": 1
    },
    {
      "tile_id": 36079,
      "x": -2,
      "y": 4,
      "z": 0,
      "flags": 1
    },
    {
      "tile_id": 36081,
      "x": 2,
      "y": 4,
      "z": 0,
      "flags": 1
    },
    {
      "tile_id": 36268,
      "x": -2,
      "y": -4,
      "z": 0,
      "flags": 1
    },
    {
      "tile_id": 36024,
      "x": -3,
      "y": -4,
      "z": 0,
      "flags": 1
    },
    {
      "tile_id": 36026,
      "x": 3,
      "y": -4,
      "z": 0,
      "flags": 1
    },
    {
      "tile_id": 36080,
      "x": -3,
      "y": 4,
      "z": 0,
      "flags": 1
    },
    {
      "tile_id": 36082,
      "x": 3,
      "y": 4,
      "z": 0,
      "flags": 1
    },
    {
      "tile_id": 36119,
      "x": 0,
      "y": -5,
      "z": 0,
      "flags": 1
    },
    {
      "tile_id": 36263,
      "x": 0,
      "y": -5,
      "z": 0,
      "flags": 1
    },
    {
      "tile_id": 36275,
      "x": 0,
      "y": 5,
      "z": 0,
      "flags": 1
    },
    {
      "tile_id": 36120,
      "x": -1,
      "y": -5,
      "z": 0,
      "flags": 1
    },
    {
      "tile_id": 36125,
      "x": 1,
      "y": -5,
      "z": 0,
      "flags": 1
    },
    {
      "tile_id": 36262,
      "x": -1,
      "y": -5,
      "z": 0,
      "flags": 1
    },
    {
      "tile_id": 36285,
      "x": -1,
      "y": 5,
      "z": 0,
      "flags": 1
    },
    {
      "tile_id": 36087,
      "x": -3,
      "y": 5,
      "z": 0,
      "flags": 1
    },
    {
      "tile_id": 36089,
      "x": 3,
      "y": 5,
      "z": 0,
      "flags": 1
    },
    {
      "tile_id": 36122,
      "x": -3,
      "y": -5,
      "z": 0,
      "flags": 1
    },
    {
      "tile_id": 36124,
      "x": 3,
      "y": -5,
      "z": 0,
      "flags": 1
    },
    {
      "tile_id": 36126,
      "x": 0,
      "y": -6,
      "z": 0,
      "flags": 1
    },
    {
      "tile_id": 36256,
      "x": 0,
      "y": -6,
      "z": 0,
      "flags": 1
    },
    {
      "tile_id": 36127,
      "x": -1,
      "y": -6,
      "z": 0,
      "flags": 1
    },
    {
      "tile_id": 36132,
      "x": 1,
      "y": -6,
      "z": 0,
      "flags": 1
    },
    {
      "tile_id": 36260,
      "x": -1,
      "y": -6,
      "z": 0,
      "flags": 1
    },
    {
      "tile_id": 36128,
      "x": -2,
      "y": -6,
      "z": 0,
      "flags": 1
    },
    {
      "tile_id": 36130,
      "x": 2,
      "y": -6,
      "z": 0,
      "flags": 1
    },
    {
      "tile_id": 36094,
      "x": -3,
      "y": 6,
      "z": 0,
      "flags": 1
    },
    {
      "tile_id": 36096,
      "x": 3,
      "y": 6,
      "z": 0,
      "flags": 1
    },
    {
      "tile_id": 36129,
      "x": -3,
      "y": -6,
      "z": 0,
      "flags": 1
    },
    {
      "tile_id": 36131,
      "x": 3,
      "y": -6,
      "z": 0,
      "flags": 1
    },
    {
      "tile_id": 36133,
      "x": 0,
      "y": -7,
      "z": 0,
      "flags": 1
    },
    {
      "tile_id": 36258,
      "x": 0,
      "y": -7,
      "z": 0,
      "flags": 1
    },
    {
      "tile_id": 36134,
      "x": -1,
      "y": -7,
      "z": 0,
      "flags": 1
    },
    {
      "tile_id": 36139,
      "x": 1,
      "y": -7,
      "z": 0,
      "flags": 1
    },
    {
      "tile_id": 36257,
      "x": -1,
      "y": -7,
      "z": 0,
      "flags": 1
    },
    {
      "tile_id": 36135,
      "x": -2,
      "y": -7,
      "z": 0,
      "flags": 1
    },
    {
      "tile_id": 36137,
      "x": 2,
      "y": -7,
      "z": 0,
      "flags": 1
    },
    {
      "tile_id": 36259,
      "x": -2,
      "y": -7,
      "z": 0,
      "flags": 1
    },
    {
      "tile_id": 36101,
      "x": -3,
      "y": 7,
      "z": 0,
      "flags": 1
    },
    {
      "tile_id": 36103,
      "x": 3,
      "y": 7,
      "z": 0,
      "flags": 1
    },
    {
      "tile_id": 36136,
      "x": -3,
      "y": -7,
      "z": 0,
      "flags": 1
    },
    {
      "tile_id": 36138,
      "x": 3,
      "y": -7,
      "z": 0,
      "flags": 1
    },
    {
      "tile_id": 36141,
      "x": -1,
      "y": -8,
      "z": 0,
      "flags": 1
    },
    {
      "tile_id": 36146,
      "x": 1,
      "y": -8,
      "z": 0,
      "flags": 1
    },
    {
      "tile_id": 36142,
      "x": -2,
      "y": -8,
      "z": 0,
      "flags": 1
    },
    {
      "tile_id": 36144,
      "x": 2,
      "y": -8,
      "z": 0,
      "flags": 1
    },
    {
      "tile_id": 36108,
      "x": -3,
      "y": 8,
      "z": 0,
      "flags": 1
    },
    {
      "tile_id": 36110,
      "x": 3,
      "y": 8,
      "z": 0,
      "flags": 1
    },
    {
      "tile_id": 36143,
      "x": -3,
      "y": -8,
      "z": 0,
      "flags": 1
    },
    {
      "tile_id": 36145,
      "x": 3,
      "y": -8,
      "z": 0,
      "flags": 1
    },
    {
      "tile_id": 36112,
      "x": 0,
      "y": 9,
      "z": 0,
      "flags": 1
    },
    {
      "tile_id": 36147,
      "x": 0,
      "y": -9,
      "z": 0,
      "flags": 1
    },
    {
      "tile_id": 36113,
      "x": -1,
      "y": 9,
      "z": 0,
      "flags": 1
    },
    {
      "tile_id": 36118,
      "x": 1,
      "y": 9,
      "z": 0,
      "flags": 1
    },
    {
      "tile_id": 36148,
      "x": -1,
      "y": -9,
      "z": 0,
      "flags": 1
    },
    {
      "tile_id": 36151,
      "x": 1,
      "y": -9,
      "z": 0,
      "flags": 1
    },
    {
      "tile_id": 36114,
      "x": -2,
      "y": 9,
      "z": 0,
      "flags": 1
    },
    {
      "tile_id": 36116,
      "x": 2,
      "y": 9,
      "z": 0,
      "flags": 1
    },
    {
      "tile_id": 36149,
      "x": -2,
      "y": -9,
      "z": 0,
      "flags": 1
    },
    {
      "tile_id": 36150,
      "x": 2,
      "y": -9,
      "z": 0,
      "flags": 1
    },
    {
      "tile_id": 36115,
      "x": -3,
      "y": 9,
      "z": 0,
      "flags": 1
    },
    {
      "tile_id": 36117,
      "x": 3,
      "y": 9,
      "z": 0,
      "flags": 1
    },
    {
      "tile_id": 36152,
      "x": 0,
      "y": -10,
      "z": 0,
      "flags": 1
    },
    {
      "tile_id": 36153,
      "x": -1,
      "y": -10,
      "z": 0,
      "flags": 1
    },
    {
      "tile_id": 36156,
      "x": 1,
      "y": -10,
      "z": 0,
      "flags": 1
    },
    {
      "tile_id": 36154,
      "x": -2,
      "y": -10,
      "z": 0,
      "flags": 1
    },
    {
      "tile_id": 36155,
      "x": 2,
      "y": -10,
      "z": 0,
      "flags": 1
    },
    {
      "tile_id": 36157,
      "x": 0,
      "y": -11,
      "z": 0,
      "flags": 1
    },
    {
      "tile_id": 36158,
      "x": -1,
      "y": -11,
      "z": 0,
      "flags": 1
    },
    {
      "tile_id": 36159,
      "x": 1,
      "y": -11,
      "z": 0,
      "flags": 1
    },
    {
      "tile_id": 36160,
      "x": 0,
      "y": -12,
      "z": 0,
      "flags": 1
    },
    {
      "tile_id": 36161,
      "x": -1,
      "y": -12,
      "z": 0,
      "flags": 1
    },
    {
      "tile_id": 36162,
      "x": 1,
      "y": -12,
      "z": 0,
      "flags": 1
    },
    {
      "tile_id": 1,
      "x": 0,
      "y": -14,
      "z": 0,
      "flags": 1
    }
  ],
  "doors": []
}
