{
  "name": "Exodus Energy Tower",
  "bounds": {
    "x1": -1,
    "y1": -1,
    "x2": 1,
    "y2": 1
  },
  "statics": [
    {
      "tile_id": 1,
      "x": 0,
      "y": 0,
      "z": 0,
      "flags": 0
    },
    {
      "tile_id": 97,
      "x": 0,
      "y": 0,
      "z": 0,
      "flags": 0
    },
    {
      "tile_id": 260,
      "x": 0,
      "y": 0,
      "z": 11,
      "flags": 0
    },
    {
      "tile_id": 107,
      "x": 0,
      "y": 0,
      "z": 31,
      "flags": 0
    },
    {
      "tile_id": 98,
      "x": 0,
      "y": 0,
      "z": 36,
      "flags": 0
    },
    {
      "tile_id": 14360,
      "x": 0,
      "y": 0,
      "z": 50,
      "flags": 1
    },
    {
      "tile_id": 118,
      "x": -1,
      "y": 1,
      "z": 0,
      "flags": 0
    },
    {
      "tile_id": 87,
      "x": -1,
      "y": 0,
      "z": 0,
      "flags": 0
    },
    {
      "tile_id": 90,
      "x": -1,
      "y": -1,
      "z": 0,
      "flags": 0
    },
    {
      "tile_id": 117,
      "x": 1,
      "y": -1,
      "z": 0,
      "flags": 0
    },
    {
      "tile_id": 88,
      "x": 0,
      "y": -1,
      "z": 0,
      "flags": 0
    },
    {
      "tile_id": 115,
      "x": 1,
      "y": 1,
      "z": 0,
      "flags": 0
    },
    {
      "tile_id": 3865,
      "x": 1,
      "y": -1,
      "z": 3,
      "flags": 1
    },
    {
      "tile_id": 3867,
      "x": -1,
      "y": 1,
      "z": 3,
      "flags": 1
    },
    {
      "tile_id": 3855,
      "x": -1,
      "y": 1,
      "z": 3,
      "flags": 1
    },
    {
      "tile_id": 3880,
      "x": 1,
      "y": -1,
      "z": 7,
      "flags": 1
    },
    {
      "tile_id": 3859,
      "x": 1,
      "y": 1,
      "z": 9,
      "flags": 1
    },
    {
      "tile_id": 3868,
      "x": 1,
      "y": 1,
      "z": 9,
      "flags": 1
    },
    {
      "tile_id": 3868,
      "x": 1,
      "y": 1,
      "z": 11,
      "flags": 1
    },
    {
      "tile_id": 3859,
      "x": 1,
      "y": 1,
      "z": 11,
      "flags": 1
    },
    {
      "tile_id": 4440,
      "x": 0,
      "y": 1,
      "z": 12,
      "flags": 1
    },
    {
      "tile_id": 4435,
      "x": 1,
      "y": 0,
      "z": 13,
      "flags": 1
    },
    {
      "tile_id": 110,
      "x": 0,
      "y": -1,
      "z": 15,
      "flags": 0
    },
    {
      "tile_id": 111,
      "x": 1,
      "y": -1,
      "z": 15,
      "flags": 0
    },
    {
      "tile_id": 113,
      "x": -1,
      "y": 1,
      "z": 15,
      "flags": 0
    },
    {
      "tile_id": 112,
      "x": -1,
      "y": 0,
      "z": 15,
      "flags": 0
    },
    {
      "tile_id": 4440,
      "x": 1,
      "y": 1,
      "z": 17,
      "flags": 1
    },
    {
      "tile_id": 4435,
      "x": 1,
      "y": 1,
      "z": 17,
      "flags": 1
    },
    {
      "tile_id": 95,
      "x": 0,
      "y": -1,
      "z": 20,
      "flags": 0
    },
    {
      "tile_id": 96,
      "x": -1,
      "y": 0,
      "z": 20,
      "flags": 0
    },
    {
      "tile_id": 98,
      "x": -1,
      "y": -1,
      "z": 20,
      "flags": 0
    },
    {
      "tile_id": 105,
      "x": 0,
      "y": -1,
      "z": 31,
      "flags": 0
    },
    {
      "tile_id": 108,
      "x": -1,
      "y": -1,
      "z": 31,
      "flags": 0
    },
    {
      "tile_id": 106,
      "x": -1,
      "y": 0,
      "z": 31,
      "flags": 0
    },
    {
      "tile_id": 98,
      "x": -1,
      "y": 0,
      "z": 36,
      "flags": 0
    },
    {
      "tile_id": 98,
      "x": 0,
      "y": -1,
      "z": 36,
      "flags": 0
    },
    {
      "tile_id": 98,
      "x": -1,
      "y": -1,
      "z": 36,
      "flags": 0
    }
  ],
  "doors": []
}
